upscrot/__init__.py
upscrot/main.py
upscrot-1.1.0.dist-info/METADATA
upscrot-1.1.0.dist-info/WHEEL
upscrot-1.1.0.dist-info/entry_points.txt
upscrot-1.1.0.dist-info/top_level.txt
upscrot-1.1.0.dist-info/RECORD
