Metadata-Version: 2.1
Name: upscrot
Version: 1.1.0
Summary: Directly upload screenshots to a SSH server.
Home-page: https://github.com/dbrgn/upscrot/
Author: Danilo Bargen
Author-email: mail@dbrgn.ch
License: GPLv3
Keywords: screenshot upload scrot ssh
Platform: UNKNOWN
Classifier: Development Status :: 4 - Beta
Classifier: Environment :: Console
Classifier: License :: OSI Approved :: GNU General Public License (GPL)
Classifier: Natural Language :: English
Classifier: Operating System :: POSIX :: Linux
Classifier: Programming Language :: Python :: 3
Classifier: Topic :: Home Automation
Classifier: Topic :: Utilities
Requires-Dist: appdirs (<2,>=1.4)
